pytest_compare/__init__.py
pytest_compare/base.py
pytest_compare/dict/__init__.py
pytest_compare/dict/dict.py
pytest_compare/native/__init__.py
pytest_compare/native/native.py
pytest_compare/pandas/__init__.py
pytest_compare/pandas/pandas.py
pytest_compare-0.2.5.dist-info/LICENSE
pytest_compare-0.2.5.dist-info/METADATA
pytest_compare-0.2.5.dist-info/WHEEL
pytest_compare-0.2.5.dist-info/top_level.txt
pytest_compare-0.2.5.dist-info/RECORD
