Metadata-Version: 2.1
Name: pytest-compare
Version: 0.2.5
Summary: pytest plugin for comparing call arguments.
Author-email: Ilya Michlin <ilyamichlin1@gmail.com>
Project-URL: homepage, https://pytesty.github.io/pytest-compare/
Project-URL: documentation, https://pytesty.github.io/pytest-compare/documentation/
Project-URL: repository, https://github.com/pytesty/pytest-compare/
Project-URL: license, https://pytesty.github.io/pytest-compare/license/
Classifier: Development Status :: 5 - Production/Stable
Classifier: Intended Audience :: Developers
Classifier: Operating System :: MacOS
Classifier: Operating System :: Microsoft :: Windows
Classifier: Operating System :: POSIX :: Linux
Classifier: Programming Language :: Python :: 3
Classifier: Programming Language :: Python :: 3 :: Only
Classifier: Programming Language :: Python :: 3.7
Classifier: Programming Language :: Python :: 3.8
Classifier: Programming Language :: Python :: 3.9
Classifier: Programming Language :: Python :: 3.10
Classifier: Programming Language :: Python :: 3.11
Requires-Python: >=3.7
License-File: LICENSE
Requires-Dist: typeguard (<4.0.0)
Provides-Extra: pandas
Requires-Dist: pandas ; extra == 'pandas'
